kudb/__init__.py
kudb/kudb.py
kudb/py.typed
kudb-0.2.8.dist-info/licenses/LICENSE
kudb-0.2.8.dist-info/METADATA
kudb-0.2.8.dist-info/WHEEL
kudb-0.2.8.dist-info/top_level.txt
kudb-0.2.8.dist-info/RECORD
