Metadata-Version: 2.4
Name: kudb
Version: 0.2.8
Summary: Simple Document database Library
Home-page: https://github.com/kujirahand/kudb
Author: kujirahand
Author-email: kujirahand <web@kujirahand.com>
Maintainer: kujirahand
Maintainer-email: kujirahand <web@kujirahand.com>
License: MIT
Project-URL: Homepage, https://github.com/kujirahand/kudb-python
Project-URL: Repository, https://github.com/kujirahand/kudb-python
Project-URL: Bug Tracker, https://github.com/kujirahand/kudb-python/issues
Project-URL: Documentation, https://github.com/kujirahand/kudb-python/blob/main/README.md
Keywords: database,document-database,key-value-store,sqlite,nosql
Classifier: Programming Language :: Python :: 3
Classifier: Programming Language :: Python :: 3.6
Classifier: Programming Language :: Python :: 3.7
Classifier: Programming Language :: Python :: 3.8
Classifier: Programming Language :: Python :: 3.9
Classifier: Programming Language :: Python :: 3.10
Classifier: Programming Language :: Python :: 3.11
Classifier: Programming Language :: Python :: 3.12
Classifier: Operating System :: OS Independent
Classifier: Development Status :: 4 - Beta
Classifier: Intended Audience :: Developers
Classifier: Topic :: Database
Classifier: Topic :: Database :: Database Engines/Servers
Classifier: Topic :: Software Development :: Libraries :: Python Modules
Requires-Python: >=3.6
License-File: LICENSE
Dynamic: author
Dynamic: home-page
Dynamic: license-file
Dynamic: maintainer
Dynamic: requires-python
